kalshi/__init__.py
kalshi/auth.py
kalshi/constants.py
kalshi/rest/__init__.py
kalshi/rest/collection.py
kalshi/rest/exchange.py
kalshi/rest/market.py
kalshi/rest/portfolio.py
kalshi/rest/rest.py
kalshi/websocket/__init__.py
kalshi/websocket/client.py
kalshi_python_unofficial-0.0.1.dist-info/LICENSE
kalshi_python_unofficial-0.0.1.dist-info/METADATA
kalshi_python_unofficial-0.0.1.dist-info/WHEEL
kalshi_python_unofficial-0.0.1.dist-info/top_level.txt
kalshi_python_unofficial-0.0.1.dist-info/RECORD
