Metadata-Version: 2.1
Name: kalshi-python-unofficial
Version: 0.0.1
Summary: A unofficial Python wrapper for the Kalshi API
Home-page: https://github.com/humz2k/kalshi-python-unofficial
Author: humz2k
Classifier: Programming Language :: Python :: 3
Classifier: License :: OSI Approved :: MIT License
Classifier: Operating System :: OS Independent
Requires-Python: >=3.7
License-File: LICENSE
Requires-Dist: websockets (>=10.0)
Requires-Dist: Requests
Requires-Dist: cryptography
